{"imagePath":"effect_05015_texture.png","SubTexture":[{"width":33,"height":37,"x":423,"y":2,"name":"0"},{"width":50,"height":48,"x":371,"y":2,"name":"1"},{"width":50,"height":50,"x":319,"y":2,"name":"2"},{"width":50,"height":52,"x":267,"y":2,"name":"3"},{"width":49,"height":55,"x":216,"y":2,"name":"4"},{"width":49,"height":57,"x":165,"y":2,"name":"5"},{"width":51,"height":58,"x":112,"y":2,"name":"6"},{"width":52,"height":58,"x":58,"y":2,"name":"7"},{"width":54,"height":59,"x":2,"y":2,"name":"8"}],"name":"effect_05015"}