{"1":{"A":1,"B":"英雄觉醒后可以获得新技能"},"2":{"A":2,"B":"技能升级需要消耗技能点"},"3":{"A":3,"B":"英雄培养可以额外增加属性"},"4":{"A":4,"B":"通关高级副本有几率掉落专属材料"},"5":{"A":5,"B":"装备进阶后强化等级不变"},"6":{"A":6,"B":"副本评分3星可以进行扫荡"},"7":{"A":7,"B":"收集英雄碎片可以兑换新英雄"},"8":{"A":8,"B":"英雄碎片可以用来进化"},"9":{"A":9,"B":"领主大人的头像是可以点击更换的哦"},"10":{"A":10,"B":"副本信息可以提前查看敌方阵容"},"11":{"A":11,"B":"长按经验道具可以连续使用"},"12":{"A":12,"B":"长按技能图标可以查看详情"},"13":{"A":13,"B":"哀嚎山谷会掉落大量材料"},"14":{"A":14,"B":"竞技场的幸运排名可以获得钻石奖励"},"15":{"A":15,"B":"精英副本可以掉落英雄碎片"},"16":{"A":16,"B":"背包里的物品有数量上限，注意不要浪费"},"17":{"A":17,"B":"领主升级可以获得新秘术"},"18":{"A":18,"B":"收集英雄可以升级秘术"},"19":{"A":19,"B":"主动秘术可以在战斗中释放"},"20":{"A":20,"B":"扫荡副本有几率触发神秘的商人"},"21":{"A":21,"B":"使用炼金术有几率触发神秘的商人"},"22":{"A":22,"B":"战魂可以更换和卸下，可灵活使用"},"23":{"A":23,"B":"专属装备最能发挥英雄的能力特点"},"24":{"A":24,"B":"战胜虚空塔守卫可获得大量金币"},"25":{"A":25,"B":"收集多位英雄以应对不同的敌人"}}